{
  "RSpec": {
    "coverage": {
      "/Users/vanessaflorio/Desktop/bookmark_challenge/bookmark_manager/spec/bookmark_spec.rb": {
        "lines": [
          1,
          1,
          null,
          1,
          1,
          1,
          1,
          1,
          1,
          null,
          null,
          1,
          1,
          null,
          7,
          null,
          1,
          1,
          1,
          null,
          null,
          null,
          null
        ]
      },
      "/Users/vanessaflorio/Desktop/bookmark_challenge/bookmark_manager/spec/features/create_bookmark_spec.rb": {
        "lines": [
          null,
          1,
          1,
          1,
          1,
          0,
          null,
          null,
          1,
          1,
          1,
          0,
          0,
          null,
          null
        ]
      },
      "/Users/vanessaflorio/Desktop/bookmark_challenge/bookmark_manager/spec/features/view_bookmark_spec.rb": {
        "lines": [
          1,
          null,
          1,
          1,
          1,
          1,
          null,
          1,
          1,
          1,
          1,
          null,
          1,
          1,
          1,
          null,
          null,
          null
        ]
      }
    },
    "timestamp": 1641922144
  }
}
